fst_runtime/__init__.py
fst_runtime/att_format_error.py
fst_runtime/fst.py
fst_runtime/semiring.py
fst_runtime/tokenize_input.py
fst_runtime-0.2.1.dist-info/LICENSE
fst_runtime-0.2.1.dist-info/METADATA
fst_runtime-0.2.1.dist-info/WHEEL
fst_runtime-0.2.1.dist-info/RECORD
