Metadata-Version: 2.1
Name: fst_runtime
Version: 0.2.1
Summary: A runtime environment for querying FSTs stored in the AT&T `.att` format.
Home-page: https://github.com/CultureFoundryCA/fst-runtime
License: MIT
Author: CultureFoundryInc.
Author-email: info@culturefoundrystudios.com
Maintainer: Scott Parkhill
Maintainer-email: contact@parkhill.tech
Requires-Python: >=3.12,<4.0
Classifier: License :: OSI Approved :: MIT License
Classifier: Programming Language :: Python :: 3
Classifier: Programming Language :: Python :: 3.12
Project-URL: Repository, https://github.com/CultureFoundryCA/fst-runtime
